setup.py
word2color/__init__.py
word2color/word2color.py
word2color.egg-info/PKG-INFO
word2color.egg-info/SOURCES.txt
word2color.egg-info/dependency_links.txt
word2color.egg-info/not-zip-safe
word2color.egg-info/requires.txt
word2color.egg-info/top_level.txt