Metadata-Version: 1.0
Name: word2color
Version: 0.1.1
Summary: Convert descriptions of colors to colors
Home-page: https://github.com/nelson-liu/word2color
Author: Nelson Liu, Aakash Sethi
Author-email: nfliu@uw.edu, aakash.k.sethi@gmail.com
License: MIT
Platform: UNKNOWN
